Metadata-Version: 1.0
Name: pacakge
Version: 0.0
Summary: Gaussian and Binomial distributions
Home-page: UNKNOWN
Author: PPPP
Author-email: purvaa1425@gmail.com
License: UNKNOWN
Platform: UNKNOWN
